{
    "drawer": [
        {
            "link": "/",
            "title": "Home"
        },
        {
            "link": "/experiences",
            "title": "Experiences"
        },
        {
            "link": "/blog",
            "title": "Blog"
        }
    ],
    "toolbar": [
        {
            "link": "/",
            "title": "Home"
        },
        {
            "link": "/experiences",
            "title": "Experiences"
        },        
        {
            "link": "/blog",
            "title": "Blog"
        }
    ]
}